jutge/relayer/relayer.py
jutge_relayer-1.0.0.dist-info/LICENSE
jutge_relayer-1.0.0.dist-info/METADATA
jutge_relayer-1.0.0.dist-info/WHEEL
jutge_relayer-1.0.0.dist-info/entry_points.txt
jutge_relayer-1.0.0.dist-info/top_level.txt
jutge_relayer-1.0.0.dist-info/RECORD
